plotxy/__init__.py
plotxy/cli.py
plotxy/exceptions.py
plotxy/figure.py
plotxy/theme.py
plotxy/cae/__init__.py
plotxy/cae/analysis.py
plotxy/cae/animation.py
plotxy/cae/fields.py
plotxy/cae/geometry.py
plotxy/cae/mesh.py
plotxy/charts/__init__.py
plotxy/charts/advanced.py
plotxy/charts/bar.py
plotxy/charts/base.py
plotxy/charts/box.py
plotxy/charts/engineering.py
plotxy/charts/financial.py
plotxy/charts/histogram.py
plotxy/charts/line.py
plotxy/charts/scatter.py
plotxy/charts/surface.py
plotxy/core/__init__.py
plotxy/core/performance.py
plotxy/core/renderer.py
plotxy/core/streaming.py
plotxy/engineering/__init__.py
plotxy/engineering/bode.py
plotxy/engineering/stress.py
plotxy/interaction3d/__init__.py
plotxy/interaction3d/animation.py
plotxy/interaction3d/camera.py
plotxy/interaction3d/gestures.py
plotxy/interaction3d/manipulation.py
plotxy/interaction3d/navigation.py
plotxy/interaction3d/scene.py
plotxy/interaction3d/selection.py
plotxy/interaction3d/vr.py
plotxy/rendering/__init__.py
plotxy/rendering/canvas.py
plotxy/rendering/export.py
plotxy/rendering/primitives.py
plotxy/rendering/renderer.py
plotxy/web/__init__.py
plotxy/web/components.py
plotxy/web/export.py
plotxy/web/server.py
plotxy-1.0.7.dist-info/licenses/LICENSE
plotxy-1.0.7.dist-info/METADATA
plotxy-1.0.7.dist-info/WHEEL
plotxy-1.0.7.dist-info/entry_points.txt
plotxy-1.0.7.dist-info/top_level.txt
plotxy-1.0.7.dist-info/RECORD
