Metadata-Version: 2.4
Name: plotxy
Version: 1.0.7
Summary: High-performance visualization library with zero dependencies
Home-page: https://github.com/plotx/plotxy
Author: Infinidatum Development Team
Author-email: Infinidatum Development Team <durai@infinidatum.net>
Maintainer-email: Infinidatum Development Team <durai@infinidatum.net>
License: MIT License
Project-URL: Homepage, https://github.com/plotx/plotxy
Project-URL: Documentation, https://plotxy.readthedocs.io/
Project-URL: Repository, https://github.com/plotx/plotxy
Project-URL: Bug Tracker, https://github.com/plotx/plotxy/issues
Project-URL: Examples, https://github.com/plotx/plotxy/tree/main/examples
Keywords: visualization,plotting,charts,graphs,data-science,matplotlib-alternative,plotly-alternative,zero-dependencies,3d-visualization,interactive-charts,financial-charts,real-time-plotting,high-performance,pure-python,scientific-visualization,engineering-plots,dashboard
Classifier: Development Status :: 5 - Production/Stable
Classifier: Intended Audience :: Developers
Classifier: Intended Audience :: Science/Research
Classifier: Intended Audience :: Financial and Insurance Industry
Classifier: Intended Audience :: Education
Classifier: Topic :: Scientific/Engineering :: Visualization
Classifier: Topic :: Scientific/Engineering :: Information Analysis
Classifier: Topic :: Multimedia :: Graphics
Classifier: Topic :: Software Development :: Libraries :: Python Modules
Classifier: License :: OSI Approved :: MIT License
Classifier: Programming Language :: Python :: 3
Classifier: Programming Language :: Python :: 3.7
Classifier: Programming Language :: Python :: 3.8
Classifier: Programming Language :: Python :: 3.9
Classifier: Programming Language :: Python :: 3.10
Classifier: Programming Language :: Python :: 3.11
Classifier: Programming Language :: Python :: 3.12
Classifier: Operating System :: OS Independent
Classifier: Environment :: Console
Classifier: Environment :: Web Environment
Requires-Python: >=3.7
License-File: LICENSE
Requires-Dist: numpy>=1.19.0
Requires-Dist: tornado>=6.0.0
Requires-Dist: jupyter>=1.0.0
Requires-Dist: ipywidgets>=7.0.0
Provides-Extra: dev
Requires-Dist: pytest>=6.0.0; extra == "dev"
Requires-Dist: pytest-cov>=2.10.0; extra == "dev"
Requires-Dist: black>=21.0.0; extra == "dev"
Requires-Dist: flake8>=3.8.0; extra == "dev"
Requires-Dist: mypy>=0.800; extra == "dev"
Provides-Extra: web
Requires-Dist: tornado>=6.0.0; extra == "web"
Provides-Extra: jupyter
Requires-Dist: jupyter>=1.0.0; extra == "jupyter"
Requires-Dist: ipywidgets>=7.0.0; extra == "jupyter"
Provides-Extra: complete
Requires-Dist: tornado>=6.0.0; extra == "complete"
Requires-Dist: jupyter>=1.0.0; extra == "complete"
Requires-Dist: ipywidgets>=7.0.0; extra == "complete"
Dynamic: author
Dynamic: home-page
Dynamic: license-file
Dynamic: requires-python
